[{"id":"federations.10000","type":"country_event","namespace":"federations","title_key":"federations.10000.name","desc_keys":[{"text":"federations.10000.desc"}],"picture":"GFX_evt_engineering_research","options":[{"name_key":"progress.2.a.mech","allow":null,"trigger":null,"ai_chance":null,"effects":[],"triggered_events":[],"custom_tooltip":null}],"trigger":null,"immediate":null,"after":null,"is_triggered_only":true,"hide_window":false,"fire_only_once":false,"diplomatic":false,"mean_time_to_happen":null,"location":null,"triggered_events":[],"source_file":"federations_events_1.txt","on_actions":[],"triggered_by":[],"triggers_events":[]},{"id":"federations.10010","type":"country_event","namespace":"federations","title_key":"federations.10010.name","desc_keys":[{"text":"federations.10010.desc","trigger":[{"is_gestalt":"no"}]},{"text":"federations.10010.desc_gestalt","trigger":[{"is_gestalt":"yes"}]}],"picture":"GFX_evt_alien_propaganda","options":[{"name_key":"EXCELLENT","allow":null,"trigger":null,"ai_chance":null,"effects":[],"triggered_events":[],"custom_tooltip":"greater_than_ourselves_tooltip"}],"trigger":null,"immediate":null,"after":null,"is_triggered_only":true,"hide_window":false,"fire_only_once":false,"diplomatic":false,"mean_time_to_happen":null,"location":null,"triggered_events":[],"source_file":"federations_events_1.txt","on_actions":[],"triggered_by":[],"triggers_events":[]},{"id":"federations.10020","type":"country_event","namespace":"federations","title_key":"federations.10020.name","desc_keys":[{"text":"federations.10020.desc","trigger":[{"is_gestalt":"no"}]},{"text":"federations.10020.desc_gestalt","trigger":[{"is_gestalt":"yes"}]}],"picture":"GFX_evt_clocks","options":[{"name_key":"EXCELLENT","allow":null,"trigger":null,"ai_chance":null,"effects":[],"triggered_events":[],"custom_tooltip":"extradimensional_experimentation_tooltip"}],"trigger":null,"immediate":null,"after":null,"is_triggered_only":true,"hide_window":false,"fire_only_once":false,"diplomatic":false,"mean_time_to_happen":null,"location":null,"triggered_events":[],"source_file":"federations_events_1.txt","on_actions":[],"triggered_by":[],"triggers_events":[]},{"id":"federations.type","type":"country_event","namespace":"federations","title_key":"Change federation type","desc_keys":[{"text":"NAME_Fluffy"}],"picture":"GFX_evt_zro_1","options":[{"name_key":"default_federation","allow":null,"trigger":[{"has_federation":"yes"},{"federation":[{"NOT":[{"has_federation_type":"default_federation"}]}]}],"ai_chance":null,"effects":[{"federation":[{"set_federation_type":"default_federation"}]}],"triggered_events":[],"custom_tooltip":null},{"name_key":"trade_federation","allow":null,"trigger":[{"has_federation":"yes"},{"federation":[{"NOT":[{"has_federation_type":"trade_federation"}]}]}],"ai_chance":null,"effects":[{"federation":[{"set_federation_type":"trade_federation"}]}],"triggered_events":[],"custom_tooltip":null},{"name_key":"research_federation","allow":null,"trigger":[{"has_federation":"yes"},{"federation":[{"NOT":[{"has_federation_type":"research_federation"}]}]}],"ai_chance":null,"effects":[{"federation":[{"set_federation_type":"research_federation"}]}],"triggered_events":[],"custom_tooltip":null},{"name_key":"military_federation","allow":null,"trigger":[{"has_federation":"yes"},{"federation":[{"NOT":[{"has_federation_type":"military_federation"}]}]}],"ai_chance":null,"effects":[{"federation":[{"set_federation_type":"military_federation"}]}],"triggered_events":[],"custom_tooltip":null},{"name_key":"hegemony_federation","allow":null,"trigger":[{"has_federation":"yes"},{"federation":[{"NOT":[{"has_federation_type":"hegemony_federation"}]}]}],"ai_chance":null,"effects":[{"federation":[{"set_federation_type":"hegemony_federation"}]}],"triggered_events":[],"custom_tooltip":null},{"name_key":"sth_nevermind","allow":null,"trigger":null,"ai_chance":null,"effects":[],"triggered_events":[],"custom_tooltip":null}],"trigger":[{"always":"no"}],"immediate":null,"after":null,"is_triggered_only":true,"hide_window":false,"fire_only_once":false,"diplomatic":false,"mean_time_to_happen":null,"location":null,"triggered_events":[],"source_file":"federations_events_1.txt","on_actions":[],"triggered_by":[],"triggers_events":[]},{"id":"federations.10100","type":"country_event","namespace":"federations","title_key":"resolution_galacticstudies_advanced_xenostudies","desc_keys":[{"text":"federations.10100.desc"}],"picture":"GFX_evt_galactic_senate","options":[{"name_key":"FED_WE_MUST_COMPLY","allow":null,"trigger":[{"AND":[{"can_set_ai_policy":"yes"},{"has_policy_flag":"ai_outlawed"}]},{"AND":[{"has_met_primitives":"yes"},{"has_policy_flag":"interference_not_allowed"}]}],"ai_chance":null,"effects":[{"set_policy":[{"policy":"artificial_intelligence_policy"},{"option":"ai_servitude"},{"cooldown":"yes"}]},{"set_policy":[{"policy":"interference"},{"option":"interference_active"},{"cooldown":"yes"}]}],"triggered_events":[],"custom_tooltip":"federations.10100.change_ai"},{"name_key":"FED_WE_MUST_COMPLY","allow":null,"trigger":[{"AND":[{"can_set_ai_policy":"yes"},{"has_policy_flag":"ai_outlawed"}]},{"OR":[{"has_met_primitives":"no"},{"NOT":[{"has_policy_flag":"interference_not_allowed"}]}]}],"ai_chance":null,"effects":[{"set_policy":[{"policy":"artificial_intelligence_policy"},{"option":"ai_servitude"},{"cooldown":"yes"}]}],"triggered_events":[],"custom_tooltip":"federations.10100.change_ai"},{"name_key":"FED_WE_MUST_COMPLY","allow":null,"trigger":[{"AND":[{"has_met_primitives":"yes"},{"has_policy_flag":"interference_not_allowed"}]},{"OR":[{"can_set_ai_policy":"no"},{"NOT":[{"has_policy_flag":"ai_outlawed"}]}]}],"ai_chance":null,"effects":[{"set_policy":[{"policy":"interference"},{"option":"interference_active"},{"cooldown":"yes"}]}],"triggered_events":[],"custom_tooltip":"federations.10100.change_interference"},{"name_key":"FED_WE_WILL_RETAIN","allow":null,"trigger":[{"NOR":[{"has_ethic":"ethic_xenophobe"},{"has_ethic":"ethic_fanatic_xenophobe"},{"has_ethic":"ethic_spiritualist"},{"has_ethic":"ethic_fanatic_spiritualist"}]}],"ai_chance":null,"effects":[{"add_monthly_resource_mult":[{"resource":"unity"},{"value":"@tier1unityreward"},{"min":"@tier1unitymin"},{"max":"@tier1unitymax"}]}],"triggered_events":[],"custom_tooltip":"FED_WE_WILL_BE_IN_BREACH"},{"name_key":"FED_WE_WILL_NOT_SUBMIT","allow":null,"trigger":[{"OR":[{"has_ethic":"ethic_xenophobe"},{"has_ethic":"ethic_fanatic_xenophobe"},{"has_ethic":"ethic_spiritualist"},{"has_ethic":"ethic_fanatic_spiritualist"}]}],"ai_chance":null,"effects":[{"add_monthly_resource_mult":[{"resource":"unity"},{"value":"@tier2unityreward"},{"min":"@tier2unitymin"},{"max":"@tier2unitymax"}]}],"triggered_events":[],"custom_tooltip":"FED_WE_WILL_BE_IN_BREACH"}],"trigger":null,"immediate":null,"after":null,"is_triggered_only":true,"hide_window":false,"fire_only_once":false,"diplomatic":false,"mean_time_to_happen":null,"location":null,"triggered_events":[],"source_file":"federations_events_1.txt","on_actions":[],"triggered_by":[],"triggers_events":[]},{"id":"federations.10110","type":"country_event","namespace":"federations","title_key":"resolution_galacticstudies_ethical_guideline_refactoring","desc_keys":[{"text":"federations.10110.desc"}],"picture":"GFX_evt_galactic_senate","options":[{"name_key":"FED_WE_MUST_COMPLY","allow":[{"NOR":[{"has_ethic":"ethic_egalitarian"},{"has_ethic":"ethic_fanatic_egalitarian"}]}],"trigger":[{"has_technology":"tech_capacity_boosters"},{"NOT":[{"has_policy_flag":"leader_enhancement_capacity_boosters"}]}],"ai_chance":null,"effects":[{"set_policy":[{"policy":"leader_enhancement"},{"option":"leader_enhancement_capacity_boosters"},{"cooldown":"yes"}]}],"triggered_events":[],"custom_tooltip":"federations.10110.capacity_boosters"},{"name_key":"FED_WE_MUST_COMPLY","allow":[{"NOT":[{"has_ethic":"ethic_fanatic_egalitarian"}]}],"trigger":[{"NOT":[{"has_technology":"tech_capacity_boosters"}]},{"has_technology":"tech_selected_lineages"},{"has_policy_flag":"leader_enhancement_natural_selection"}],"ai_chance":null,"effects":[{"set_policy":[{"policy":"leader_enhancement"},{"option":"leader_enhancement_selected_lineages"},{"cooldown":"yes"}]}],"triggered_events":[],"custom_tooltip":"federations.10110.selected_lineages"},{"name_key":"FED_WE_WILL_RETAIN","allow":null,"trigger":[{"NOR":[{"has_ethic":"ethic_xenophobe"},{"has_ethic":"ethic_fanatic_xenophobe"},{"has_ethic":"ethic_egalitarian"},{"has_ethic":"ethic_fanatic_egalitarian"}]}],"ai_chance":null,"effects":[{"add_monthly_resource_mult":[{"resource":"unity"},{"value":"@tier1unityreward"},{"min":"@tier1unitymin"},{"max":"@tier1unitymax"}]}],"triggered_events":[],"custom_tooltip":"FED_WE_WILL_BE_IN_BREACH"},{"name_key":"FED_WE_WILL_NOT_SUBMIT","allow":null,"trigger":[{"OR":[{"has_ethic":"ethic_xenophobe"},{"has_ethic":"ethic_fanatic_xenophobe"},{"has_ethic":"ethic_egalitarian"},{"has_ethic":"ethic_fanatic_egalitarian"}]}],"ai_chance":null,"effects":[{"add_monthly_resource_mult":[{"resource":"unity"},{"value":"@tier2unityreward"},{"min":"@tier2unitymin"},{"max":"@tier2unitymax"}]}],"triggered_events":[],"custom_tooltip":"FED_WE_WILL_BE_IN_BREACH"}],"trigger":null,"immediate":null,"after":null,"is_triggered_only":true,"hide_window":false,"fire_only_once":false,"diplomatic":false,"mean_time_to_happen":null,"location":null,"triggered_events":[],"source_file":"federations_events_1.txt","on_actions":[],"triggered_by":[],"triggers_events":[]},{"id":"federations.10300","type":"country_event","namespace":"federations","title_key":"resolution_rulesofwar_reverence_for_life","desc_keys":[{"text":"federations.10300.desc"}],"picture":"GFX_evt_galactic_senate","options":[{"name_key":"FED_WE_MUST_COMPLY","allow":null,"trigger":null,"ai_chance":null,"effects":[{"hidden_effect":[{"set_policy":[{"policy":"purge"},{"option":"purge_displacement_only"},{"cooldown":"yes"}]}]}],"triggered_events":[],"custom_tooltip":"federations.10300.comply"},{"name_key":"FED_WE_WILL_RETAIN","allow":null,"trigger":[{"NOR":[{"has_ethic":"ethic_xenophobe"},{"has_ethic":"ethic_fanatic_xenophobe"}]}],"ai_chance":null,"effects":[{"add_monthly_resource_mult":[{"resource":"unity"},{"value":"@tier1unityreward"},{"min":"@tier1unitymin"},{"max":"@tier1unitymax"}]}],"triggered_events":[],"custom_tooltip":"FED_WE_WILL_BE_IN_BREACH"},{"name_key":"FED_WE_WILL_NOT_SUBMIT","allow":null,"trigger":[{"OR":[{"has_ethic":"ethic_xenophobe"},{"has_ethic":"ethic_fanatic_xenophobe"}]}],"ai_chance":null,"effects":[{"add_monthly_resource_mult":[{"resource":"unity"},{"value":"@tier2unityreward"},{"min":"@tier2unitymin"},{"max":"@tier2unitymax"}]}],"triggered_events":[],"custom_tooltip":"FED_WE_WILL_BE_IN_BREACH"}],"trigger":null,"immediate":null,"after":null,"is_triggered_only":true,"hide_window":false,"fire_only_once":false,"diplomatic":false,"mean_time_to_happen":null,"location":null,"triggered_events":[],"source_file":"federations_events_1.txt","on_actions":[],"triggered_by":[],"triggers_events":[]},{"id":"federations.10310","type":"country_event","namespace":"federations","title_key":"resolution_rulesofwar_independent_tribunals","desc_keys":[{"text":"federations.10310.desc"}],"picture":"GFX_evt_galactic_senate","options":[{"name_key":"FED_WE_MUST_COMPLY","allow":null,"trigger":null,"ai_chance":null,"effects":[{"hidden_effect":[{"set_policy":[{"policy":"orbital_bombardment"},{"option":"orbital_bombardment_selective"},{"cooldown":"yes"}]}]}],"triggered_events":[],"custom_tooltip":"federations.10310.comply"},{"name_key":"FED_WE_WILL_RETAIN","allow":null,"trigger":[{"NOR":[{"has_ethic":"ethic_xenophobe"},{"has_ethic":"ethic_fanatic_xenophobe"},{"has_ethic":"ethic_militarist"},{"has_ethic":"ethic_fanatic_militarist"}]}],"ai_chance":null,"effects":[{"add_monthly_resource_mult":[{"resource":"unity"},{"value":"@tier1unityreward"},{"min":"@tier1unitymin"},{"max":"@tier1unitymax"}]}],"triggered_events":[],"custom_tooltip":"FED_WE_WILL_BE_IN_BREACH"},{"name_key":"FED_WE_WILL_NOT_SUBMIT","allow":null,"trigger":[{"OR":[{"has_ethic":"ethic_xenophobe"},{"has_ethic":"ethic_fanatic_xenophobe"},{"has_ethic":"ethic_militarist"},{"has_ethic":"ethic_fanatic_militarist"}]}],"ai_chance":null,"effects":[{"add_monthly_resource_mult":[{"resource":"unity"},{"value":"@tier2unityreward"},{"min":"@tier2unitymin"},{"max":"@tier2unitymax"}]}],"triggered_events":[],"custom_tooltip":"FED_WE_WILL_BE_IN_BREACH"}],"trigger":null,"immediate":null,"after":null,"is_triggered_only":true,"hide_window":false,"fire_only_once":false,"diplomatic":false,"mean_time_to_happen":null,"location":null,"triggered_events":[],"source_file":"federations_events_1.txt","on_actions":[],"triggered_by":[],"triggers_events":[]},{"id":"federations.10320","type":"country_event","namespace":"federations","title_key":"resolution_rulesofwar_last_resort_doctrine","desc_keys":[{"text":"federations.10320.desc"}],"picture":"GFX_evt_galactic_senate","options":[{"name_key":"FED_WE_MUST_COMPLY","allow":null,"trigger":[{"NOT":[{"has_ethic":"ethic_gestalt_consciousness"}]}],"ai_chance":null,"effects":[{"hidden_effect":[{"set_policy":[{"policy":"war_philosophy"},{"option":"ideological_wars"},{"cooldown":"yes"}]}]}],"triggered_events":[],"custom_tooltip":"federations.10320.comply"},{"name_key":"FED_WE_MUST_COMPLY","allow":null,"trigger":[{"has_ethic":"ethic_gestalt_consciousness"}],"ai_chance":null,"effects":[{"hidden_effect":[{"set_policy":[{"policy":"war_philosophy"},{"option":"no_wars"},{"cooldown":"yes"}]}]}],"triggered_events":[],"custom_tooltip":"federations.10320.complygestalt"},{"name_key":"FED_WE_WILL_RETAIN","allow":null,"trigger":[{"NOR":[{"has_ethic":"ethic_xenophobe"},{"has_ethic":"ethic_fanatic_xenophobe"},{"has_ethic":"ethic_militarist"},{"has_ethic":"ethic_fanatic_militarist"}]}],"ai_chance":null,"effects":[{"add_monthly_resource_mult":[{"resource":"unity"},{"value":"@tier1unityreward"},{"min":"@tier1unitymin"},{"max":"@tier1unitymax"}]}],"triggered_events":[],"custom_tooltip":"FED_WE_WILL_BE_IN_BREACH"},{"name_key":"FED_WE_WILL_NOT_SUBMIT","allow":null,"trigger":[{"OR":[{"has_ethic":"ethic_xenophobe"},{"has_ethic":"ethic_fanatic_xenophobe"},{"has_ethic":"ethic_militarist"},{"has_ethic":"ethic_fanatic_militarist"}]}],"ai_chance":null,"effects":[{"add_monthly_resource_mult":[{"resource":"unity"},{"value":"@tier2unityreward"},{"min":"@tier2unitymin"},{"max":"@tier2unitymax"}]}],"triggered_events":[],"custom_tooltip":"FED_WE_WILL_BE_IN_BREACH"}],"trigger":null,"immediate":null,"after":null,"is_triggered_only":true,"hide_window":false,"fire_only_once":false,"diplomatic":false,"mean_time_to_happen":null,"location":null,"triggered_events":[],"source_file":"federations_events_1.txt","on_actions":[],"triggered_by":[],"triggers_events":[]},{"id":"federations.10330","type":"country_event","namespace":"federations","title_key":"resolution_rulesofwar_demobilization_initiative","desc_keys":[{"text":"federations.10330.desc"}],"picture":"GFX_evt_galactic_senate","options":[{"name_key":"FED_WE_MUST_COMPLY","allow":null,"trigger":null,"ai_chance":null,"effects":[{"hidden_effect":[{"set_policy":[{"policy":"economic_policy"},{"option":"economic_policy_balanced"},{"cooldown":"yes"}]}]}],"triggered_events":[],"custom_tooltip":"federations.10330.comply"},{"name_key":"FED_WE_WILL_RETAIN","allow":null,"trigger":[{"NOR":[{"has_ethic":"ethic_xenophobe"},{"has_ethic":"ethic_fanatic_xenophobe"},{"has_ethic":"ethic_militarist"},{"has_ethic":"ethic_fanatic_militarist"}]}],"ai_chance":null,"effects":[{"add_monthly_resource_mult":[{"resource":"unity"},{"value":"@tier1unityreward"},{"min":"@tier1unitymin"},{"max":"@tier1unitymax"}]}],"triggered_events":[],"custom_tooltip":"FED_WE_WILL_BE_IN_BREACH"},{"name_key":"FED_WE_WILL_NOT_SUBMIT","allow":null,"trigger":[{"OR":[{"has_ethic":"ethic_xenophobe"},{"has_ethic":"ethic_fanatic_xenophobe"},{"has_ethic":"ethic_militarist"},{"has_ethic":"ethic_fanatic_militarist"}]}],"ai_chance":null,"effects":[{"add_monthly_resource_mult":[{"resource":"unity"},{"value":"@tier2unityreward"},{"min":"@tier2unitymin"},{"max":"@tier2unitymax"}]}],"triggered_events":[],"custom_tooltip":"FED_WE_WILL_BE_IN_BREACH"}],"trigger":null,"immediate":null,"after":null,"is_triggered_only":true,"hide_window":false,"fire_only_once":false,"diplomatic":false,"mean_time_to_happen":null,"location":null,"triggered_events":[],"source_file":"federations_events_1.txt","on_actions":[],"triggered_by":[],"triggers_events":[]}]